{
  "1": {
    "inputs": {
      "torchscript_jit": "default",
      "image": [
        "2",
        0
      ]
    },
    "class_type": "InspyrenetRembg",
    "_meta": {
      "title": "Inspyrenet Rembg"
    }
  },
  "2": {
    "inputs": {
      "image": "",
      "upload": "image"
    },
    "class_type": "LoadImage",
    "_meta": {
      "title": "Load Image"
    }
  },
  "3": {
    "inputs": {
      "images": [
        "1",
        0
      ]
    },
    "class_type": "PreviewImage",
    "_meta": {
      "title": "Preview Image"
    }
  },
  "5": {
    "inputs": {
      "mask": [
        "1",
        1
      ]
    },
    "class_type": "MaskToImage",
    "_meta": {
      "title": "Convert Mask to Image"
    }
  },
  "6": {
    "inputs": {
      "images": [
        "5",
        0
      ]
    },
    "class_type": "PreviewImage",
    "_meta": {
      "title": "Preview Image"
    }
  }
}